[{"name":"definitely","pronunciation":{"uk":{"source":[{"type":"audio/mpeg","src":"/audio/en/uk/general/en023284.mp3"}],"class":"uk","phonetic":"/ˈdɛfɪnɪtli/"},"us":{"source":[{"type":"audio/mpeg","src":"/audio/en/us/us/en023284.mp3"}],"class":"us","phonetic":"/ˈdɛfənɪtli/, (def′ə nit lē)"}},"dsense":[{"name":"definitely","pos":"adv","guideword":" (certainly, undoubtedly)","trans_examp":[{"example":[{"eg":"The student definitely appreciates the scholarship money.","egtrans":"该名学生肯定很重视这一奖学金。//他的高级资历肯定也有所助益。"}],"trans_cn":"肯定"}]}]},{"name":"definitely","pronunciation":{"uk":{"source":[{"type":"audio/mpeg","src":"/audio/en/uk/general/en023284.mp3"}],"class":"uk","phonetic":"/ˈdɛfɪnɪtli/"},"us":{"source":[{"type":"audio/mpeg","src":"/audio/en/us/us/en023284.mp3"}],"class":"us","phonetic":"/ˈdɛfənɪtli/, (def′ə nit lē)"}},"dsense":[{"name":"definitely","pos":"adv","guideword":" (distinctly, clearly)","trans_examp":[{"example":[{"eg":"First I'll think about it, and then I'll answer more definitely.","egtrans":"我先要考虑一下，然后再明确回答。"}],"trans_cn":"清楚地, 明确地"}]},{"name":"definitely","pos":"interj","guideword":" (indicates emphatic assent) (加强语气)","trans_examp":[{"example":[{"eg":"Definitely!  I'd love to come to a karaoke night!","egtrans":"当然！我非常愿意晚上去唱卡拉ＯＫ！　"}],"trans_cn":"当然，肯定"}]}]}]