[{"name":"execution","pronunciation":{"uk":{"source":[{"type":"audio/mpeg","src":"/audio/en/uk/general/en031521.mp3"}],"class":"uk","phonetic":"/ˌɛksɪˈkjuːʃən/"},"us":{"source":[{"type":"audio/mpeg","src":"/audio/en/us/us/en031521.mp3"}],"class":"us","phonetic":"/ˌɛksɪˈkjuʃən/, (ek′si kyo̅o̅′shən)"}},"dsense":[{"name":"execution","pos":"n","guideword":" (prisoner)","trans_examp":[{"example":[{"eg":"The murderer's execution is due to take place at the end of the month.","egtrans":""}],"trans_cn":"死刑, 处死, 处决"}]},{"name":"execution","pos":"n","guideword":" (killing) (职业杀手)","trans_examp":[{"example":[{"eg":"Police said the murder looked like an execution and they were investigating links between the victim and criminal gangs.","egtrans":""}],"trans_cn":"处决，杀害"}]},{"name":"execution","pos":"n","guideword":" (of a plan)","trans_examp":[{"example":[{"eg":"The thieves' execution of their plan to rob the bank was flawless and they got away with a lot of money.","egtrans":""}],"trans_cn":"执行, 实施"}]},{"name":"execution","pos":"n","guideword":" (legal: enforcing)","trans_examp":[{"example":[{"eg":"The judge was determined in his execution of the law.","egtrans":""}],"trans_cn":"履行"}]},{"name":"execution","pos":"n","guideword":" (technique)","trans_examp":[{"example":[{"eg":"The painter's work is interesting, but his execution is poor.","egtrans":""}],"trans_cn":"技术, 技巧, 手法"}]}]},{"name":"execution","pronunciation":{"uk":{"source":[{"type":"audio/mpeg","src":"/audio/en/uk/general/en031521.mp3"}],"class":"uk","phonetic":"/ˌɛksɪˈkjuːʃən/"},"us":{"source":[{"type":"audio/mpeg","src":"/audio/en/us/us/en031521.mp3"}],"class":"us","phonetic":"/ˌɛksɪˈkjuʃən/, (ek′si kyo̅o̅′shən)"}},"dsense":[{"name":"stay of execution","pos":"n","guideword":" (law: suspension of court order) (法律)","trans_examp":[{"example":[{}],"trans_cn":"执行中止"}]}]}]