[{"name":"make sense","pronunciation":{},"dsense":[{"name":"make sense","pos":"v expr","guideword":" (be logical)","trans_examp":[{"example":[{"eg":"It makes sense to book train tickets in advance because they are cheaper.","egtrans":""}],"trans_cn":"有道理, 说得通"}]},{"name":"make sense","pos":"v expr","guideword":" (be comprehensible)","trans_examp":[{"example":[{"eg":"After her stroke nothing the patient said made sense.","egtrans":""}],"trans_cn":"能够被理解, 能让人听得明白"}]},{"name":"make sense of [sth]","pos":"v expr","guideword":" (work out meaning of)","trans_examp":[{"example":[{"eg":"The Egyptologist tried to make sense of the hieroglyphics.","egtrans":""}],"trans_cn":"了解，弄明白, 理解"}]}]},{"name":"make sense","pronunciation":{},"dsense":[{"name":"not make sense","pos":"v expr","guideword":" (be illogical)","trans_examp":[{"example":[{"eg":"It does not make sense to butter your bread with axle grease.","egtrans":""}],"trans_cn":"讲不通, 不合情理, 不合逻辑"}]},{"name":"not make sense","pos":"v expr","guideword":" (be incomprehensible)","trans_examp":[{"example":[{"eg":"Ainsley was drunk and what he was saying was not making sense.","egtrans":""}],"trans_cn":"难以理解, 难以听懂"}]}]}]