[{"name":"post","pronunciation":{"uk":{"source":[{"type":"audio/mpeg","src":"/audio/en/uk/general/en065718.mp3"}],"class":"uk","phonetic":"/ˈpəʊst/"},"us":{"source":[{"type":"audio/mpeg","src":"/audio/en/us/us/en065718.mp3"}],"class":"us","phonetic":"/poʊst/, (pōst)"}},"dsense":[{"name":"post","pos":"n","guideword":" UK, uncountable (mail  delivery)","trans_examp":[{"example":[{"eg":"The bill is going out in today's post.","egtrans":"账单已经随同今天的邮件发出了。"}],"trans_cn":"邮件"}]},{"name":"post","pos":"n","guideword":" UK, uncountable (mail: letters, parcels, etc.)","trans_examp":[{"example":[{"eg":"Can you check today's post for the letter from the bank?","egtrans":"你能查看一下今天的邮件里有银行的来信吗？"}],"trans_cn":"邮件, 邮包"}]},{"name":"post","pos":"n","guideword":" UK, uncountable (mail delivery system)","trans_examp":[{"example":[{"eg":"The post is slow in rural areas.","egtrans":"农村地区的邮政系统很慢。"}],"trans_cn":"邮政系统, 邮递系统, 邮寄系统"}]},{"name":"post","pos":"n","guideword":" (job, position)","trans_examp":[{"example":[{"eg":"Lee was hired for a post in government.","egtrans":"李受聘在政府里担任职务。"}],"trans_cn":"工作, 职位, 职务"}]},{"name":"post","pos":"n","guideword":" (military station)","trans_examp":[{"example":[{"eg":"The soldiers were sent to a surveillance post near the front lines.","egtrans":"士兵们被派往前线附近的一个监测军事哨岗。"}],"trans_cn":"军事岗哨"}]},{"name":"post","pos":"n","guideword":" (military camp)","trans_examp":[{"example":[{"eg":"The sergeant is respected on this post.","egtrans":"这位中士在这个军营很受人尊敬。"}],"trans_cn":"军营, 军队驻扎之地"}]},{"name":"post [sth]⇒","pos":"vtr","guideword":" UK (send by mail)","trans_examp":[{"example":[{"eg":"I posted the letter today.","egtrans":"我今天寄出了一封信。"}],"trans_cn":"寄出, 邮寄"}]},{"name":"post [sth]","pos":"vtr","guideword":" (display on notice board, etc.)","trans_examp":[{"example":[{"eg":"The professor posted the test results in the hallway.","egtrans":"教授把考试成绩张贴在过道里。"}],"trans_cn":"张贴"}]},{"name":"post [sth]","pos":"vtr","guideword":" (share on internet) (在网上)","trans_examp":[{"example":[{"eg":"She posted her favorite quote on her profile page.","egtrans":"她把自己最喜欢的一句话在个人主页上发布了出来。"}],"trans_cn":"把…发布出来"}]}]},{"name":"post","pronunciation":{"uk":{"source":[{"type":"audio/mpeg","src":"/audio/en/uk/general/en065718.mp3"}],"class":"uk","phonetic":"/ˈpəʊst/"},"us":{"source":[{"type":"audio/mpeg","src":"/audio/en/us/us/en065718.mp3"}],"class":"us","phonetic":"/poʊst/, (pōst)"}},"dsense":[{"name":"post","pos":"n","guideword":" (place where task is carried out)","trans_examp":[{"example":[{"eg":"Last year, Janine helped construct wells at her post in Africa.","egtrans":""}],"trans_cn":"职位, 职务"}]},{"name":"post","pos":"n","guideword":" (trading post)","trans_examp":[{"example":[{"eg":"The trappers entered the trading post.","egtrans":"捕兽者进入了交易站。"}],"trans_cn":"贸易站, 交易站"}]},{"name":"post","pos":"n","guideword":" (pole)","trans_examp":[{"example":[{"eg":"The car hit a post.","egtrans":"那辆车撞上了柱子。"}],"trans_cn":"杆, 柱"}]},{"name":"post","pos":"n","guideword":" (goalpost)","trans_examp":[{"example":[{"eg":"The ball bounced off the post.","egtrans":"球从球门柱上弹了回来。"}],"trans_cn":"球门柱"}]},{"name":"post","pos":"n","guideword":" (forum message)","trans_examp":[{"example":[{"eg":"The third post in the thread had the answer he was looking for.","egtrans":"话题的第三条回帖就有他要的答案。"}],"trans_cn":"帖子, 论坛发帖"}]},{"name":"post","pos":"n","guideword":" (rod used to repair tooth structure) (用于修复牙齿结构)","trans_examp":[{"example":[{"eg":"The dentist fitted her with a post to keep the crown stable.","egtrans":""}],"trans_cn":"桩"}]},{"name":"post, post-","pos":"prefix","guideword":" (after, later) (前缀)","trans_examp":[{"example":[{"eg":"On Sundays I enjoy a post-lunch stroll in the park.  The country experienced an economic boom in the postwar years.","egtrans":"周日吃完午饭后，我会去公园里散个步。战后数年中，这个国家的经济取得了高速发展。"}],"trans_cn":"后面的，之后的，后"}]},{"name":"post [sth]","pos":"vtr","guideword":" (cover with posters)","trans_examp":[{"example":[{"eg":"The boys posted the fence with concert advertisements.","egtrans":""}],"trans_cn":"在...上贴满广告, 在...上贴满告示"}]},{"name":"post [sth]","pos":"vtr","guideword":" (publish, advertise)","trans_examp":[{"example":[{"eg":"The company posted the job vacancies in the newspaper.","egtrans":""}],"trans_cn":"公布, 发布"}]},{"name":"post [sth]","pos":"vtr","guideword":" US (score) (体育比赛)","trans_examp":[{"example":[{"eg":"The visiting team posted a goal in the first half.","egtrans":""}],"trans_cn":"得...分"}]},{"name":"post [sth]","pos":"vtr","guideword":" (mark in a ledger)","trans_examp":[{"example":[{"eg":"The business posted a profit.","egtrans":""}],"trans_cn":"在账本上标记为"}]},{"name":"post [sth]","pos":"vtr","guideword":" (update a ledger)","trans_examp":[{"example":[{"eg":"Post today's numbers in the general ledger.","egtrans":""}],"trans_cn":"把…入账"}]},{"name":"post [sb] to [sth]","pos":"vtr + prep","guideword":" often passive (assign [sb] to a station)","trans_examp":[{"example":[{"eg":"The enlisted man was posted to a sniper unit near the town.","egtrans":"这位应征入伍的士兵被派遣到了小镇附近的一个狙击小队中。"}],"trans_cn":"派遣（某人）到（某岗位）"}]},{"name":"post [sb] to [sth]","pos":"vtr + prep","guideword":" (assign [sb] to a job)","trans_examp":[{"example":[{"eg":"She was posted from headquarters to a field office.","egtrans":"她被调离了总部，分配到一个外地办事处工作。"}],"trans_cn":"分配（某人）到…工作"}]}]},{"name":"post","pronunciation":{"uk":{"source":[{"type":"audio/mpeg","src":"/audio/en/uk/general/en065718.mp3"}],"class":"uk","phonetic":"/ˈpəʊst/"},"us":{"source":[{"type":"audio/mpeg","src":"/audio/en/us/us/en065718.mp3"}],"class":"us","phonetic":"/poʊst/, (pōst)"}},"dsense":[{"name":"post [sth] up, post up [sth]","pos":"vtr phrasal sep","guideword":" (display: a notice, etc.) (通知、公告等)","trans_examp":[{"example":[{"eg":"The manager posted up the team selection in the changing room an hour before the game.","egtrans":""}],"trans_cn":"张贴, 公布, 贴出"}]}]},{"name":"post","pronunciation":{"uk":{"source":[{"type":"audio/mpeg","src":"/audio/en/uk/general/en065718.mp3"}],"class":"uk","phonetic":"/ˈpəʊst/"},"us":{"source":[{"type":"audio/mpeg","src":"/audio/en/us/us/en065718.mp3"}],"class":"us","phonetic":"/poʊst/, (pōst)"}},"dsense":[{"name":"blogpost, blog post","pos":"n","guideword":" (online diary entry)","trans_examp":[{"example":[{"eg":"","egtrans":""}],"trans_cn":"博文, 博客文章"}]},{"name":"by post","pos":"adv","guideword":" (through the mail)","trans_examp":[{"example":[{"eg":"Can you either fax it to me or send it by post?","egtrans":""}],"trans_cn":"邮寄"}]},{"name":"ex post","pos":"","guideword":" Latin (based on analysis) (拉丁语)","trans_examp":[{"example":[{}],"trans_cn":"根据分析"}]},{"name":"fence post","pos":"n","guideword":" (stake or picket of a fence)","trans_examp":[{"example":[{"eg":"You should install the fence posts in postholes that are deep enough to go below the frostline.","egtrans":""}],"trans_cn":"围栏桩，栅栏桩"}]},{"name":"first-past-the-post","pos":"adj","guideword":" (winner of race)","trans_examp":[{"example":[{"eg":"Pete won some money because he bet on the horse that was first-past-the-post.","egtrans":""}],"trans_cn":"获胜的"}]},{"name":"first-past-the-post","pos":"n","guideword":" (election by simple majority)","trans_examp":[{"example":[{"eg":"First-past-the-post is the electoral system used to elect parliament in the UK.","egtrans":""}],"trans_cn":"得票最多者当选"}]},{"name":"from pillar to post","pos":"expr","guideword":" figurative (from place to place)","trans_examp":[{"example":[{"eg":"","egtrans":""}],"trans_cn":"东奔西跑, 四处奔波"}]},{"name":"from pillar to post","pos":"expr","guideword":" figurative (from one bad situation to another)","trans_examp":[{"example":[{"eg":"","egtrans":""}],"trans_cn":"四处碰壁, 走投无路"}]},{"name":"general post office","pos":"n","guideword":" US (main post office branch)","trans_examp":[{"example":[{"eg":"The general post office is located in the neighborhood of Chelsea.","egtrans":""}],"trans_cn":"邮政总局"}]},{"name":"goalpost, goal post","pos":"n","guideword":" (upright bar indicating goal area) (本义)","trans_examp":[{"example":[{"eg":"The football player danced under the goalpost.","egtrans":""}],"trans_cn":"球门门柱"}]},{"name":"hitching post","pos":"n","guideword":" (post to which animal is fastened)","trans_examp":[{"example":[{"eg":"The cowboy tied his horse to the hitching post outside the saloon and went in for a beer.","egtrans":""}],"trans_cn":"拴马柱"}]},{"name":"in the mail, also UK: in the post","pos":"adj","guideword":" (in postal system)","trans_examp":[{"example":[{"eg":"My application is in the mail, so you should be receiving it soon.","egtrans":""}],"trans_cn":"寄出去的，在邮递过程中的"}]},{"name":"lamppost, also UK: lamp post","pos":"n","guideword":" (post of a street lamp)","trans_examp":[{"example":[{"eg":"The street was lined with trees and lampposts.","egtrans":""}],"trans_cn":"路灯杆, 街灯柱"}]},{"name":"listening post","pos":"n","guideword":" (position for obtaining information on an enemy)","trans_examp":[{"example":[{"eg":"The intelligence services set up secret listening posts behind enemy lines.","egtrans":""}],"trans_cn":"潜听哨"}]},{"name":"mailbox (US), postbox, pillar box (UK)","pos":"n","guideword":" (in street: post box)","trans_examp":[{"example":[{"eg":"The mailbox is emptied twice a day.","egtrans":""}],"trans_cn":"信箱, 邮箱"}]},{"name":"observation post","pos":"n","guideword":" (lookout, observation point)","trans_examp":[{"example":[{"eg":"The army has set up a series of observation posts.","egtrans":""}],"trans_cn":"观测点, 观察所, 观察所"}]},{"name":"parcel post","pos":"n","guideword":" (postal service for packages)","trans_examp":[{"example":[{}],"trans_cn":"包裹邮递，包裹邮寄"}]},{"name":"parcel post","pos":"n","guideword":" US (postal rate packages)","trans_examp":[{"example":[{}],"trans_cn":"包裹邮递费，包裹邮费"}]},{"name":"parcel post receipt","pos":"n","guideword":" (acknowledgement)","trans_examp":[{"example":[{"eg":"The parcel post receipt is proof that the delivery has been carried out.","egtrans":""}],"trans_cn":"邮包收据"}]},{"name":"picture post card, picture postcard","pos":"n","guideword":" (postcard with a scenic view)","trans_examp":[{"example":[{"eg":"She sent a picture postcard of the Alps to her mother.","egtrans":""}],"trans_cn":"风景画明信片"}]},{"name":"post bail for [sb]","pos":"v expr","guideword":" (pay for [sb]'s release from prison)","trans_examp":[{"example":[{"eg":"The thief sits in jail because no one would post bail for him.","egtrans":""}],"trans_cn":"为...支付保释金"}]},{"name":"post card, postcard","pos":"n","guideword":" (souvenir greetings card)","trans_examp":[{"example":[{"eg":"Don't forget to send me a postcard.","egtrans":""}],"trans_cn":"贺卡"}]},{"name":"post card, postcard","pos":"n","guideword":" (card for posting without envelope)","trans_examp":[{"example":[{"eg":"Entries for the competition should be sent on a postcard to the following address.","egtrans":""}],"trans_cn":"明信片"}]},{"name":"post hoc","pos":"adv","guideword":" (after the fact)","trans_examp":[{"example":[{"eg":"Analysis of the results of the experiment were completed post hoc.","egtrans":""}],"trans_cn":"在此之后, 发生在这之后"}]},{"name":"post meridiem","pos":"adv","guideword":" Latin (in the afternoon, evening)","trans_examp":[{"example":[{"eg":"The meeting commenced at three o'clock, post meridiem.","egtrans":""}],"trans_cn":"下午"}]},{"name":"post office","pos":"n","guideword":" (place where mail is sorted) (指地点)","trans_examp":[{"example":[{"eg":"I'm going to the post office to send this parcel to my brother.","egtrans":"我要去邮局把这个包裹寄给我哥哥。"}],"trans_cn":"邮局, 邮政信箱"}]},{"name":"Post Script, post script","pos":"n","guideword":" (P.S.: addition to a letter) (信函后追加额外信息)","trans_examp":[{"example":[{"eg":"James had added a Post Script at the end of his letter.","egtrans":""}],"trans_cn":"附启, 另"}]},{"name":"post secondary, post-secondary","pos":"adj","guideword":" (education: tertiary)","trans_examp":[{"example":[{"eg":"The scheme is intended to address the specific needs of post-secondary students.","egtrans":""}],"trans_cn":"第三级的, 专科以上的, 专科以上的"}]},{"name":"post-accident","pos":"adj","guideword":" (after an accident)","trans_examp":[{"example":[{"eg":"The patient was suffering from post-accident shock.","egtrans":""}],"trans_cn":"事故后的"}]},{"name":"post-coital","pos":"adj","guideword":" (after sexual intercourse)","trans_examp":[{"example":[{}],"trans_cn":"性交后的"}]},{"name":"post-consumer","pos":"adj","guideword":" (recycled)","trans_examp":[{"example":[{"eg":"The company produces post-consumer recycled plastic products.","egtrans":""}],"trans_cn":"消费后的"}]},{"name":"post-departure","pos":"adj","guideword":" (after leaving)","trans_examp":[{"example":[{}],"trans_cn":"离开后的"}]},{"name":"post-impressionism","pos":"n","guideword":" (art movement)","trans_examp":[{"example":[{}],"trans_cn":"后印象派"}]},{"name":"post-impressionist","pos":"adj","guideword":" (of early 1900s art movement)","trans_examp":[{"example":[{}],"trans_cn":"后印象主义的"}]},{"name":"Post-it note, post-it note, Post-it, Post-it note","pos":"n","guideword":" ® (adhesive notepaper)","trans_examp":[{"example":[{"eg":"I left a Post-it note on the fridge door, reminding Anna to buy some milk.","egtrans":""}],"trans_cn":"便利贴"}]},{"name":"post-menopausal woman","pos":"n","guideword":" (female who no longer menstruates)","trans_examp":[{"example":[{"eg":"","egtrans":""}],"trans_cn":"绝经后的妇女, 后真相的"}]},{"name":"postcode, postal code, post code","pos":"n","guideword":" UK (zip code, address code)","trans_examp":[{"example":[{"eg":"What is the postcode for your home in London?","egtrans":""}],"trans_cn":"邮政编码, 邮递区号"}]},{"name":"postdoctoral, also UK: post-doctoral","pos":"adj","guideword":" (taking place after a PhD)","trans_examp":[{"example":[{}],"trans_cn":"博士后的"}]},{"name":"posthaste, post-haste, post haste","pos":"adv","guideword":" (as quickly as possible)","trans_examp":[{"example":[{"eg":"If you haven't already explained the delay to the boss, I suggest you do so posthaste - or there'll be trouble!","egtrans":""}],"trans_cn":"迅速地, 特别快地"}]},{"name":"postindustrial, also UK: post-industrial","pos":"adj","guideword":" (not dependent on industry anymore)","trans_examp":[{"example":[{"eg":"Many post-industrial cities have suffered an economic decline.","egtrans":""}],"trans_cn":"后工业化的, 工业社会后的"}]},{"name":"postmenopausal, post-menopausal","pos":"adj","guideword":" (woman: no longer menstruating) (指女性)","trans_examp":[{"example":[{}],"trans_cn":"绝经后的，绝经的"}]},{"name":"postmenopausal, post-menopausal","pos":"adj","guideword":" (period: after the menopause) (指时期)","trans_examp":[{"example":[{}],"trans_cn":"绝经后的"}]},{"name":"postmortem, also UK: post-mortem","pos":"n","guideword":" Latin (autopsy, examination of a corpse)","trans_examp":[{"example":[{"eg":"The postmortem showed death by natural causes.","egtrans":""}],"trans_cn":"尸检, 验尸"}]},{"name":"postmortem, also UK: post-mortem","pos":"n","guideword":" figurative, Latin (analysis after an event)","trans_examp":[{"example":[{"eg":"The coach organized a postmortem to discuss why the team lost.","egtrans":""}],"trans_cn":"事后分析, 事后调查"}]},{"name":"postmortem, also UK: post-mortem","pos":"adj","guideword":" Latin (taking place after death)","trans_examp":[{"example":[{"eg":"","egtrans":""}],"trans_cn":"死后的, 死后发生的"}]},{"name":"postmortem examination, also UK: post-mortem examination","pos":"n","guideword":" (autopsy)","trans_examp":[{"example":[{"eg":"They don't know how he died – that's why they're doing a post-mortem examination.","egtrans":""}],"trans_cn":"验尸, 尸体解剖检查"}]},{"name":"postoperative, also UK: post-operative","pos":"adj","guideword":" (after surgery)","trans_examp":[{"example":[{"eg":"When the hospital discharged Susan, they gave her information regarding her post-operative care at home.","egtrans":""}],"trans_cn":"手术后的, 术后的"}]},{"name":"postpartum, post-partum","pos":"adj","guideword":" (occurring after childbirth)","trans_examp":[{"example":[{}],"trans_cn":"产后的"}]},{"name":"postpartum, post-partum","pos":"adv","guideword":" (after childbirth)","trans_examp":[{"example":[{"eg":"Medical advice is that it is best for breastfeeding to continue until at least six months postpartum, if possible.","egtrans":""}],"trans_cn":"产后的"}]},{"name":"postpartum, post-partum","pos":"n","guideword":" US, informal, abbreviation (postpartum depression)","trans_examp":[{"example":[{}],"trans_cn":"产后抑郁症"}]},{"name":"postprandial, post-prandial","pos":"adj","guideword":" formal (after a meal)","trans_examp":[{"example":[{"eg":"","egtrans":""}],"trans_cn":"正餐后的, 餐后的"}]},{"name":"postwar, also UK: post-war","pos":"adj","guideword":" (after a war)","trans_examp":[{"example":[{}],"trans_cn":"战后的"}]},{"name":"postwar, also UK: post-war","pos":"adj","guideword":" (after the Second World War)","trans_examp":[{"example":[{"eg":"Post-war Japan experienced tremendous economic growth.","egtrans":""}],"trans_cn":"二战后的"}]},{"name":"registered mail (US), registered post (UK)","pos":"n","guideword":" (insured first-class letters, parcels)","trans_examp":[{"example":[{"eg":"We recommend that valuable items be sent by registered mail.  I'd like to send this parcel by registered post, please.","egtrans":""}],"trans_cn":"挂号邮件, 挂号信"}]},{"name":"scratching post","pos":"n","guideword":" (cat claw sharpening apparatus)","trans_examp":[{"example":[{"eg":"","egtrans":""}],"trans_cn":"猫抓板, 磨抓器"}]},{"name":"staging post, staging area","pos":"n","guideword":" (troop assembly area before setting off)","trans_examp":[{"example":[{}],"trans_cn":"补给站"}]},{"name":"staging post, staging area","pos":"n","guideword":" (any area of assembly before setting off)","trans_examp":[{"example":[{"eg":"","egtrans":""}],"trans_cn":"中转站, 中途站"}]},{"name":"telephone pole, telegraph pole, telegraph post","pos":"n","guideword":" (structure supporting phone lines)","trans_examp":[{"example":[{}],"trans_cn":"电话线杆"}]},{"name":"trading post","pos":"n","guideword":" (store in unsettled region)","trans_examp":[{"example":[{"eg":"","egtrans":""}],"trans_cn":"交易站, 贸易站"}]},{"name":"vacant post","pos":"n","guideword":" (available position, job to be filled)","trans_examp":[{"example":[{"eg":"I've heard there's a vacant post in this company.","egtrans":""}],"trans_cn":"空缺的职位, 空着的职务"}]}]}]