[{"name":"process","pronunciation":{"uk":{"source":[{"type":"audio/mpeg","src":"/audio/en/uk/general/en067032.mp3"}],"class":"uk","phonetic":" noun: /ˈprəʊsɛs/,  verb: /prəˈsɛs/"},"us":{"source":[{"type":"audio/mpeg","src":"/audio/en/us/us/en067032.mp3"}],"class":"us","phonetic":"/ˈprɑsɛs/, (pros′es; esp. Brit. prō′ses)"}},"dsense":[{"name":"process","pos":"n","guideword":" (method)","trans_examp":[{"example":[{"eg":"The chair-manufacturing process is quite complex.","egtrans":"生产椅子的工序挺复杂的。"}],"trans_cn":"工序, 加工方法, 制作方法"}]},{"name":"process","pos":"n","guideword":" (procedure)","trans_examp":[{"example":[{"eg":"There is a set process for applying for a passport.","egtrans":"申请护照有一套固定程序。"}],"trans_cn":"程序, 手续"}]},{"name":"process","pos":"n","guideword":" (systematic actions)","trans_examp":[{"example":[{"eg":"You must follow the same process every time you do it.","egtrans":"你每次都应该按照相同的步骤进行。"}],"trans_cn":"程序, 步骤"}]},{"name":"process","pos":"n","guideword":" (time: course)","trans_examp":[{"example":[{"eg":"Throughout the process, he stayed loyal to his beliefs.","egtrans":"在这整个过程中，他都对自己的信仰保持忠心。"}],"trans_cn":"过程, 期间"}]}]},{"name":"process","pronunciation":{"uk":{"source":[{"type":"audio/mpeg","src":"/audio/en/uk/general/en067032.mp3"}],"class":"uk","phonetic":" noun: /ˈprəʊsɛs/,  verb: /prəˈsɛs/"},"us":{"source":[{"type":"audio/mpeg","src":"/audio/en/us/us/en067032.mp3"}],"class":"us","phonetic":"/ˈprɑsɛs/, (pros′es; esp. Brit. prō′ses)"}},"dsense":[{"name":"process","pos":"adj","guideword":" US (food: prepared by a process)","trans_examp":[{"example":[{"eg":"The process cheese doesn't look or taste like real cheese.","egtrans":""}],"trans_cn":"加工过的"}]},{"name":"process","pos":"n","guideword":" (law: summons) (法律)","trans_examp":[{"example":[{"eg":"The process was served by a bailiff.","egtrans":""}],"trans_cn":"传票，法院传唤"}]},{"name":"process","pos":"n","guideword":" (anatomy, zoology: protuberance)","trans_examp":[{"example":[{"eg":"This bony process is called the sacral promontory.","egtrans":""}],"trans_cn":"突起"}]},{"name":"process⇒","pos":"vi","guideword":" formal (move in a procession)","trans_examp":[{"example":[{"eg":"The royal party processed from Buckingham Palace to Westminster for the wedding.","egtrans":""}],"trans_cn":"列队前进"}]},{"name":"process [sth]⇒","pos":"vtr","guideword":" (treat) (用化学药品等)","trans_examp":[{"example":[{"eg":"We need to process this in a chemical solution to make it change colour.","egtrans":""}],"trans_cn":"处理"}]},{"name":"process [sth]","pos":"vtr","guideword":" (convert)","trans_examp":[{"example":[{"eg":"Process the wood to make charcoal for cooking.","egtrans":""}],"trans_cn":"加工, 处理"}]},{"name":"process [sth/sb]⇒","pos":"vtr","guideword":" (handle systematically)","trans_examp":[{"example":[{"eg":"The immigrants were processed at the airport.","egtrans":""}],"trans_cn":"按程序办理, 按程序处理"}]},{"name":"process [sth]⇒","pos":"vtr","guideword":" (begin legal process)","trans_examp":[{"example":[{"eg":"This case must be processed efficiently or we might lose in court.","egtrans":""}],"trans_cn":"按法律程序处理"}]},{"name":"process [sth]","pos":"vtr","guideword":" (deal with [sth] emotionally) (感情)","trans_examp":[{"example":[{"eg":"Each of us processes grief in our own way.","egtrans":"我们所有人都用自己的方式处理悲伤的情感。"}],"trans_cn":"处理"}]},{"name":"process [sb] with [sth]","pos":"vtr + prep","guideword":" often passive (serve a summons) (法院传票)","trans_examp":[{"example":[{"eg":"He was processed with a summons to appear in court by the police.","egtrans":"警方把法院传票送达给他。"}],"trans_cn":"把…送达"}]},{"name":"process [sth] into [sth]","pos":"vtr + prep","guideword":" (convert) (比喻)","trans_examp":[{"example":[{"eg":"Since his stroke, Phil takes much longer to process words into sentences.","egtrans":"中风之后，菲尔要花更长的时间，才能连词为句。"}],"trans_cn":"将…加工为，将…转化为"}]}]},{"name":"process","pronunciation":{"uk":{"source":[{"type":"audio/mpeg","src":"/audio/en/uk/general/en067032.mp3"}],"class":"uk","phonetic":" noun: /ˈprəʊsɛs/,  verb: /prəˈsɛs/"},"us":{"source":[{"type":"audio/mpeg","src":"/audio/en/us/us/en067032.mp3"}],"class":"us","phonetic":"/ˈprɑsɛs/, (pros′es; esp. Brit. prō′ses)"}},"dsense":[{"name":"canning process","pos":"n","guideword":" (process of putting food in tins)","trans_examp":[{"example":[{}],"trans_cn":"罐装工艺"}]},{"name":"due process, due process of law","pos":"n","guideword":" (legal proceedings)","trans_examp":[{"example":[{"eg":"If arrested, you have the right to due process.","egtrans":""}],"trans_cn":"法定诉讼程序"}]},{"name":"due process","pos":"n","guideword":" (standard procedure)","trans_examp":[{"example":[{}],"trans_cn":"标准程序"}]},{"name":"four-color process (US), four-colour process (UK)","pos":"n","guideword":" (four-hue printing method) (美式拼法)","trans_examp":[{"example":[{}],"trans_cn":"四色印刷"}]},{"name":"freezing process","pos":"n","guideword":" (procedure for making [sth] frozen)","trans_examp":[{"example":[{}],"trans_cn":"冷冻程序"}]},{"name":"in process","pos":"adv","guideword":" (underway, ongoing)","trans_examp":[{"example":[{"eg":"Preparations for the 2012 Olympics were in process.","egtrans":"2012年奥运会的准备工作正在进行中。"}],"trans_cn":"进行中, 正在进行"}]},{"name":"in-process","pos":"adj","guideword":" (goods: in manufacture)","trans_examp":[{"example":[{"eg":"","egtrans":""}],"trans_cn":"正在生产, 正在制造, 正在加工"}]},{"name":"in the process","pos":"expr","guideword":" (while doing [sth])","trans_examp":[{"example":[{"eg":"Janine has been studying German at school, and in the process, she's made new friends.","egtrans":""}],"trans_cn":"在这个过程中, 在此过程中"}]},{"name":"in the process of [sth]","pos":"expr","guideword":" (during, in the course of)","trans_examp":[{"example":[{"eg":"The robber tripped and broke his leg in the process of trying to flee.","egtrans":""}],"trans_cn":"在…的过程中"}]},{"name":"be in the process of doing [sth]","pos":"v expr","guideword":" (be doing)","trans_examp":[{"example":[{"eg":"I am in the process of applying for a visa to travel to the USA.","egtrans":""}],"trans_cn":"正在…"}]},{"name":"legal process","pos":"n","guideword":" (court procedure)","trans_examp":[{"example":[{"eg":"The legal process to get squatters out of a property can take a long time.","egtrans":""}],"trans_cn":"法律程序"}]},{"name":"process schedule","pos":"n","guideword":" (timetable for a plan of action)","trans_examp":[{"example":[{}],"trans_cn":"行动计划时间表，进度时间表"}]},{"name":"selection process","pos":"n","guideword":" (procedure for choosing [sth] or [sb])","trans_examp":[{"example":[{}],"trans_cn":"甄选程序，遴选程序，筛选程序"}]},{"name":"service of process","pos":"n","guideword":" (law: notice of action) (法律)","trans_examp":[{"example":[{}],"trans_cn":"传票送达"}]},{"name":"thought process","pos":"n","guideword":" (thinking, train of thought)","trans_examp":[{"example":[{"eg":"","egtrans":""}],"trans_cn":"思考过程, 思路"}]}]}]