[{"name":"prove","pronunciation":{"uk":{"source":[{"type":"audio/mpeg","src":"/audio/en/uk/general/en067744.mp3"}],"class":"uk","phonetic":"/ˈpruːv/"},"us":{"source":[{"type":"audio/mpeg","src":"/audio/en/us/us/en067744.mp3"}],"class":"us","phonetic":"/pruv/, (pro̅o̅v)"}},"dsense":[{"name":"prove [sth]/that⇒","pos":"vtr","guideword":" (demonstrate conclusively)","trans_examp":[{"example":[{"eg":"The scientist attempted to prove his theory.","egtrans":"这位科学家试图证明自己的理论。"}],"trans_cn":"证明, 证实"}]},{"name":"prove [sth]⇒","pos":"vtr","guideword":" (turn out to be)","trans_examp":[{"example":[{"eg":"His conclusion proved false.","egtrans":"他的结论结果是错的。"}],"trans_cn":"结果是"}]},{"name":"prove to be [sth]","pos":"v expr","guideword":" (turn out to be)","trans_examp":[{"example":[{"eg":"The detective's hunch proved to be right.","egtrans":"侦探的预感被证明是对的。"}],"trans_cn":"事实证明…"}]},{"name":"prove⇒","pos":"vi","guideword":" (bread dough: rise) (面团)","trans_examp":[{"example":[{"eg":"Allow the dough to prove for two hours before shaping it into a loaf.","egtrans":"在将面团做成条状面包的形状前先要让它发酵两小时。"}],"trans_cn":"发酵"}]},{"name":"prove [sth], also US: proof [sth]⇒","pos":"vtr","guideword":" (bread dough: leave to rise) (面团)","trans_examp":[{"example":[{"eg":"You will need to prove the dough before baking it.","egtrans":"在烘焙前要先等面团发酵。"}],"trans_cn":"使…发酵"}]}]},{"name":"prove","pronunciation":{"uk":{"source":[{"type":"audio/mpeg","src":"/audio/en/uk/general/en067744.mp3"}],"class":"uk","phonetic":"/ˈpruːv/"},"us":{"source":[{"type":"audio/mpeg","src":"/audio/en/us/us/en067744.mp3"}],"class":"us","phonetic":"/pruv/, (pro̅o̅v)"}},"dsense":[{"name":"prove [sth]⇒","pos":"vtr","guideword":" (mathematics) (数学定理等)","trans_examp":[{"example":[{"eg":"To prove the theorem, you must show your work.","egtrans":""}],"trans_cn":"证明"}]},{"name":"prove [sth]","pos":"vtr","guideword":" (will: validate) (遗嘱)","trans_examp":[{"example":[{"eg":"The will was proved by his widow.","egtrans":""}],"trans_cn":"使...生效，认证"}]},{"name":"prove yourself","pos":"vtr + refl","guideword":" (demonstrate your worth, skill, etc.)","trans_examp":[{"example":[{"eg":"With his older siblings being high achievers, James feels he has to prove himself.","egtrans":""}],"trans_cn":"证明你自己"}]}]},{"name":"prove","pronunciation":{"uk":{"source":[{"type":"audio/mpeg","src":"/audio/en/uk/general/en067744.mp3"}],"class":"uk","phonetic":"/ˈpruːv/"},"us":{"source":[{"type":"audio/mpeg","src":"/audio/en/us/us/en067744.mp3"}],"class":"us","phonetic":"/pruv/, (pro̅o̅v)"}},"dsense":[{"name":"have nothing to prove","pos":"v expr","guideword":" (not need to justify)","trans_examp":[{"example":[{}],"trans_cn":"不需要证明什么"}]},{"name":"prove the point","pos":"v expr","guideword":" (show that [sth] is true)","trans_examp":[{"example":[{"eg":"Harry claimed that he was good at cooking and to prove the point, he would prepare a meal for us.","egtrans":""}],"trans_cn":"证实论点, 证明观点"}]},{"name":"prove true","pos":"vi + adj","guideword":" (be borne out, be shown to be accurate)","trans_examp":[{"example":[{"eg":"If these allegations prove true, the governor will be in big trouble.","egtrans":""}],"trans_cn":"证明为真实, 证明为准确"}]},{"name":"prove [sb] wrong","pos":"vtr + adj","guideword":" (show that [sb] is incorrect)","trans_examp":[{"example":[{"eg":"My father said I would never be an athlete; I'm determined to prove him wrong.","egtrans":""}],"trans_cn":"证明…错了"}]},{"name":"prove your point, prove a point","pos":"v expr","guideword":" (show you are correct)","trans_examp":[{"example":[{"eg":"Rod gave a very convincing demonstration that proved his point.","egtrans":""}],"trans_cn":"证明你的观点"}]}]}]