[{"name":"reduce","pronunciation":{"uk":{"source":[{"type":"audio/mpeg","src":"/audio/en/uk/general/en070606.mp3"}],"class":"uk","phonetic":"/rɪˈdjuːs/"},"us":{"source":[{"type":"audio/mpeg","src":"/audio/en/us/us/en070606.mp3"}],"class":"us","phonetic":"/rɪˈdus, -ˈdjus/, (ri do̅o̅s′, -dyo̅o̅s′)"}},"dsense":[{"name":"reduce [sth]⇒","pos":"vtr","guideword":" (lessen, decrease)","trans_examp":[{"example":[{"eg":"Now Trevor has lost his job, he needs to reduce his monthly outgoings.","egtrans":"现在特莱福失去了自己的工作，需要减少每月的开销。"}],"trans_cn":"使变少, 减少"}]},{"name":"reduce [sth] to [sth]","pos":"vtr + prep","guideword":" (lessen, decrease)","trans_examp":[{"example":[{"eg":"By extending the term of her mortgage, Jane reduced her monthly payments to £400.","egtrans":"简延长了自己的贷款还款期限，将每月分期付款减少到400英镑。"}],"trans_cn":"将…减少到, 使…变少到"}]},{"name":"reduce [sth]","pos":"vtr","guideword":" (rate, etc.: lower) (利率、税率、通货膨胀率等)","trans_examp":[{"example":[{"eg":"The bank has lowered the interest rate on our mortgage.","egtrans":""}],"trans_cn":"降低…率"}]},{"name":"reduce [sth] to [sth]","pos":"vtr + prep","guideword":" (rate, etc.: lower) (汇率等)","trans_examp":[{"example":[{"eg":"The Bank of England has reduced interest rates to 0.5%.","egtrans":"英格兰银行已经将利率降到0.5％。"}],"trans_cn":"降低到"}]},{"name":"reduce [sth]","pos":"vtr","guideword":" (lower the quantity of)","trans_examp":[{"example":[{"eg":"The factory had to reduce its staff due to a lack of demand for its product.","egtrans":"因为产品的需求不足，工厂只能裁减员工。"}],"trans_cn":"减少, 消减, 裁减"}]},{"name":"reduce [sth] to [sth]","pos":"vtr + prep","guideword":" (lower the quantity to)","trans_examp":[{"example":[{"eg":"Ian is giving up smoking and has reduced the number of cigarettes he smokes each day to three.","egtrans":"伊安正在戒烟，将每天抽的烟削减到三根。"}],"trans_cn":"将…削减到, 将…缩减至"}]},{"name":"reduce [sth]","pos":"vtr","guideword":" (copy: make smaller)","trans_examp":[{"example":[{"eg":"I need to reduce this A3 poster so that it will fit onto a sheet of A4.","egtrans":"我需要将这张A3的海报缩小一些，以便将其放进A4纸上。"}],"trans_cn":"缩小"}]},{"name":"reduce⇒","pos":"vi","guideword":" (lessen, decrease)","trans_examp":[{"example":[{"eg":"The number of visitors to this town has reduced in recent years.","egtrans":"近年来，到镇上旅游的访客减少了。"}],"trans_cn":"变少, 减少"}]}]},{"name":"reduce","pronunciation":{"uk":{"source":[{"type":"audio/mpeg","src":"/audio/en/uk/general/en070606.mp3"}],"class":"uk","phonetic":"/rɪˈdjuːs/"},"us":{"source":[{"type":"audio/mpeg","src":"/audio/en/us/us/en070606.mp3"}],"class":"us","phonetic":"/rɪˈdus, -ˈdjus/, (ri do̅o̅s′, -dyo̅o̅s′)"}},"dsense":[{"name":"reduce [sb] to doing [sth]","pos":"v expr","guideword":" often passive (worsen status of)","trans_examp":[{"example":[{"eg":"A once-wealthy woman, she has been reduced to begging in the street.","egtrans":""}],"trans_cn":"使沦落"}]},{"name":"reduce [sb] to doing [sth]","pos":"v expr","guideword":" usually passive (make resort to)","trans_examp":[{"example":[{"eg":"We were so poor back then that we were reduced to living on peanut butter and crackers.","egtrans":""}],"trans_cn":"使…不得不, 使…被迫做"}]},{"name":"reduce [sth]⇒","pos":"vtr","guideword":" (cookery: boil down) (汤等)","trans_examp":[{"example":[{"eg":"Reduce the wine by boiling it in a saucepan.","egtrans":""}],"trans_cn":"使...浓缩"}]},{"name":"reduce [sth]","pos":"vtr","guideword":" (mathematics: simplify) (数学)","trans_examp":[{"example":[{"eg":"The fraction 5/10 can be reduced to 1/2.","egtrans":""}],"trans_cn":"约分, 约化"}]},{"name":"reduce [sth]","pos":"vtr","guideword":" (broken bone: set)","trans_examp":[{"example":[{"eg":"Surgery was needed to reduce the fractured bone.","egtrans":""}],"trans_cn":"复位"}]},{"name":"reduce [sth] to [sth]","pos":"vtr + prep","guideword":" (simplify, condense)","trans_examp":[{"example":[{"eg":"The conflict cannot be reduced to a simple view of good versus evil.","egtrans":""}],"trans_cn":"将…概括成, 将…简化为"}]},{"name":"reduce [sth] to [sth]","pos":"vtr + prep","guideword":" (break down into: pieces)","trans_examp":[{"example":[{"eg":"The building was reduced to pieces by the force of the explosion.","egtrans":""}],"trans_cn":"使…碎成, 使…破碎成"}]},{"name":"reduce [sth] to [sth]","pos":"vtr + prep","guideword":" (idea, text: condense) (文章等)","trans_examp":[{"example":[{"eg":"That whole speech could be reduced to \"Be nice.\"","egtrans":""}],"trans_cn":"将…压缩成，使…精简为"}]},{"name":"reduce [sth/sb] to [sth]","pos":"vtr + prep","guideword":" (worsen condition of)","trans_examp":[{"example":[{"eg":"They have reduced education to rote learning and memorization.","egtrans":""}],"trans_cn":"使…沦落到, 让…沦落为"}]}]},{"name":"reduce","pronunciation":{"uk":{"source":[{"type":"audio/mpeg","src":"/audio/en/uk/general/en070606.mp3"}],"class":"uk","phonetic":"/rɪˈdjuːs/"},"us":{"source":[{"type":"audio/mpeg","src":"/audio/en/us/us/en070606.mp3"}],"class":"us","phonetic":"/rɪˈdus, -ˈdjus/, (ri do̅o̅s′, -dyo̅o̅s′)"}},"dsense":[{"name":"reduce the temperature","pos":"v expr","guideword":" (make it cooler)","trans_examp":[{"example":[{"eg":"Doctors will always try to reduce the temperature of patients with fever.","egtrans":""}],"trans_cn":"降低温度, 降温"}]}]}]