[{"name":"sponsor","pronunciation":{"uk":{"source":[{"type":"audio/mpeg","src":"/audio/en/uk/general/en082701.mp3"}],"class":"uk","phonetic":"/ˈspɒnsər/"},"us":{"source":[{"type":"audio/mpeg","src":"/audio/en/us/us/en082701.mp3"}],"class":"us","phonetic":"/ˈspɑnsɚ/, (spon′sər)"}},"dsense":[{"name":"sponsor","pos":"n","guideword":" (patron)","trans_examp":[{"example":[{"eg":"This company is the sponsor of the national rugby team.","egtrans":"这家公司是国家橄榄球队的赞助商。"}],"trans_cn":"赞助者，资助人, 主办者，发起人"}]},{"name":"sponsor","pos":"n","guideword":" (advertising) (插有自己产品广告的节目的)","trans_examp":[{"example":[{"eg":"The TV channel asked a car manufacturer to be the sponsor of its new drama series.","egtrans":"这家电视台邀请一家汽车制造商作为其新连续剧的赞助商。"}],"trans_cn":"赞助商，赞助人"}]},{"name":"sponsor [sb]⇒","pos":"vtr","guideword":" (pay expenses for)","trans_examp":[{"example":[{"eg":"The company sponsored the gifted student during his time at university.","egtrans":"公司资助那位资优学生上大学。"}],"trans_cn":"资助, 赞助"}]},{"name":"sponsor [sth/sb]⇒","pos":"vtr","guideword":" (advertise to support) (出于广告自己产品的目的)","trans_examp":[{"example":[{"eg":"A DIY store sponsors this home improvement programme on the TV.","egtrans":"一家“自己动手”商店赞助了这一家居装修电视节目。"}],"trans_cn":"赞助"}]}]},{"name":"sponsor","pronunciation":{"uk":{"source":[{"type":"audio/mpeg","src":"/audio/en/uk/general/en082701.mp3"}],"class":"uk","phonetic":"/ˈspɒnsər/"},"us":{"source":[{"type":"audio/mpeg","src":"/audio/en/us/us/en082701.mp3"}],"class":"us","phonetic":"/ˈspɑnsɚ/, (spon′sər)"}},"dsense":[{"name":"sponsor [sth]⇒","pos":"vtr","guideword":" (legislation) (立法议案)","trans_examp":[{"example":[{"eg":"The senator is sponsoring the bill.","egtrans":""}],"trans_cn":"倡议, 发起"}]}]},{"name":"sponsor","pronunciation":{"uk":{"source":[{"type":"audio/mpeg","src":"/audio/en/uk/general/en082701.mp3"}],"class":"uk","phonetic":"/ˈspɒnsər/"},"us":{"source":[{"type":"audio/mpeg","src":"/audio/en/us/us/en082701.mp3"}],"class":"us","phonetic":"/ˈspɑnsɚ/, (spon′sər)"}},"dsense":[]}]