[{"name":"store","pronunciation":{"uk":{"source":[{"type":"audio/mpeg","src":"/audio/en/uk/general/en084619.mp3"}],"class":"uk","phonetic":"/ˈstɔːr/"},"us":{"source":[{"type":"audio/mpeg","src":"/audio/en/us/us/en084619.mp3"}],"class":"us","phonetic":"/stɔr/, (stôr, stōr)"}},"dsense":[{"name":"store","pos":"n","guideword":" mainly US (shop: retail outlet)","trans_examp":[{"example":[{"eg":"We have a clothing store close to home.","egtrans":"我家附近有一个服装店。"}],"trans_cn":"商店，店铺"}]},{"name":"store","pos":"n","guideword":" (things stored)","trans_examp":[{"example":[{"eg":"We keep our store of batteries in the basement.","egtrans":"我把我们的电池储备品放在地下室。"}],"trans_cn":"贮存物, 储备品"}]},{"name":"store","pos":"n","guideword":" (place for storing)","trans_examp":[{"example":[{"eg":"They bought a cat to catch the mice that kept finding their way into the grain store.","egtrans":"他们买了只猫来抓那些总是能找到方法进到仓库的老鼠。"}],"trans_cn":"仓库, 存储处"}]},{"name":"store [sth]⇒","pos":"vtr","guideword":" (save for later)","trans_examp":[{"example":[{"eg":"I stored the rest of the cake for tomorrow.","egtrans":"我把剩余的蛋糕留起来明天吃。"}],"trans_cn":"储备, 备下"}]},{"name":"store [sth]","pos":"vtr","guideword":" (put in storage)","trans_examp":[{"example":[{"eg":"We stored the old books in the basement.","egtrans":"我们把旧书存放在地下室。"}],"trans_cn":"把…存入仓库, 存放"}]}]},{"name":"store","pronunciation":{"uk":{"source":[{"type":"audio/mpeg","src":"/audio/en/uk/general/en084619.mp3"}],"class":"uk","phonetic":"/ˈstɔːr/"},"us":{"source":[{"type":"audio/mpeg","src":"/audio/en/us/us/en084619.mp3"}],"class":"us","phonetic":"/stɔr/, (stôr, stōr)"}},"dsense":[{"name":"store","pos":"n","guideword":" (computer memory)","trans_examp":[{"example":[{"eg":"Computers have two main types of stores, main memory (RAM) and auxiliary memory (e.g. hard disks).","egtrans":"计算机主要有两种存储类型，主要存储（内存（RAM））以及辅助存储（比如：硬盘）。"}],"trans_cn":"计算机内存，计算机存储"}]},{"name":"store [sth]","pos":"vtr","guideword":" (have a capacity of)","trans_examp":[{"example":[{"eg":"This disc drive can store a huge amount of data.","egtrans":""}],"trans_cn":"可贮藏, 存储量为"}]}]},{"name":"store","pronunciation":{"uk":{"source":[{"type":"audio/mpeg","src":"/audio/en/uk/general/en084619.mp3"}],"class":"uk","phonetic":"/ˈstɔːr/"},"us":{"source":[{"type":"audio/mpeg","src":"/audio/en/us/us/en084619.mp3"}],"class":"us","phonetic":"/stɔr/, (stôr, stōr)"}},"dsense":[{"name":"store [sth] up, store up [sth]","pos":"vtr phrasal sep","guideword":" (save, keep in reserve)","trans_examp":[{"example":[{"eg":"","egtrans":""}],"trans_cn":"储存, 储备, 贮藏"}]}]},{"name":"store","pronunciation":{"uk":{"source":[{"type":"audio/mpeg","src":"/audio/en/uk/general/en084619.mp3"}],"class":"uk","phonetic":"/ˈstɔːr/"},"us":{"source":[{"type":"audio/mpeg","src":"/audio/en/us/us/en084619.mp3"}],"class":"us","phonetic":"/stɔr/, (stôr, stōr)"}},"dsense":[{"name":"app store","pos":"n","guideword":" (software purchasing portal)","trans_examp":[{"example":[{}],"trans_cn":"应用商店"}]},{"name":"big-box store","pos":"n","guideword":" (large retail unit)","trans_examp":[{"example":[{"eg":"","egtrans":""}],"trans_cn":"大型商场, 大型购物中心"}]},{"name":"bridal store, also UK: bridal shop","pos":"n","guideword":" (shop selling wedding clothes)","trans_examp":[{"example":[{"eg":"Bridal shops are reporting the usual spring increase in business.","egtrans":""}],"trans_cn":"婚纱店"}]},{"name":"candy store (US), sweet shop (UK)","pos":"n","guideword":" (confectioner's shop)","trans_examp":[{"example":[{"eg":"I am going to the candy store to buy some chocolate.","egtrans":""}],"trans_cn":"糖果屋, 糖果商店"}]},{"name":"chain store","pos":"n","guideword":" (shop with many branches)","trans_examp":[{"example":[{"eg":"Chain stores have been the death of independent retailers.","egtrans":""}],"trans_cn":"连锁商店"}]},{"name":"clothing store (US), clothes shop (UK)","pos":"n","guideword":" (shop: sells clothes)","trans_examp":[{"example":[{"eg":"The new mall has a clothing store that carries all of the styles that I like.","egtrans":""}],"trans_cn":"服装商店"}]},{"name":"cold store","pos":"n","guideword":" (refrigerated compartment)","trans_examp":[{"example":[{"eg":"","egtrans":""}],"trans_cn":"冷藏库, 冷库"}]},{"name":"cold store [sth]","pos":"vtr","guideword":" (keep in cold storage)","trans_examp":[{"example":[{"eg":"","egtrans":""}],"trans_cn":"将...存入冷藏库, 把...放入冷库"}]},{"name":"company store","pos":"n","guideword":" dated (store for employees)","trans_examp":[{"example":[{}],"trans_cn":"企业内部商店"}]},{"name":"confectionery store","pos":"n","guideword":" US (shop: sells candy)","trans_examp":[{"example":[{"eg":"Confectionery stores are rare now; most people buy sweets at grocery stores and big box stores.","egtrans":""}],"trans_cn":"糖果店, 糕点店"}]},{"name":"convenience store","pos":"n","guideword":" (small supermarket)","trans_examp":[{"example":[{"eg":"I'll just run down to the convenience store on the corner to pick up some toilet paper.","egtrans":"我要跑去楼下街角的便利店买点厕纸。"}],"trans_cn":"便利店, 方便商店, 自助小超市"}]},{"name":"dairy, dairy store","pos":"n","guideword":" NZ (small grocery store)","trans_examp":[{"example":[{"eg":"I'm off to the dairy to pick up a newspaper.","egtrans":""}],"trans_cn":"小杂货店, 小菜店"}]},{"name":"department store","pos":"n","guideword":" (large shop)","trans_examp":[{"example":[{"eg":"Macy's is a famous department store in New York City.","egtrans":"梅西百货是纽约市一家著名的百货公司。"}],"trans_cn":"百货公司"}]},{"name":"departmental store","pos":"n","guideword":" UK, dated (department store)","trans_examp":[{"example":[{"eg":"","egtrans":""}],"trans_cn":"百货商场, 百货商店"}]},{"name":"discount store","pos":"n","guideword":" (store with lower prices)","trans_examp":[{"example":[{"eg":"Wal-mart and Kmart are well-recognized American discount stores.","egtrans":""}],"trans_cn":"折扣店"}]},{"name":"dollar store (US), pound shop (UK)","pos":"n","guideword":" (shop selling cheap items)","trans_examp":[{"example":[{"eg":"These sunglasses were only a buck at the dollar store.","egtrans":""}],"trans_cn":"一元店"}]},{"name":"drugstore, drug store","pos":"n","guideword":" US (pharmacy and general shop)","trans_examp":[{"example":[{"eg":"Mary drove to the drug store to buy aspirin.","egtrans":""}],"trans_cn":"药房, 药店"}]},{"name":"dry goods store","pos":"n","guideword":" (shop: sells fabrics, clothing)","trans_examp":[{"example":[{"eg":"You won't find groceries or hardware at a dry goods store.","egtrans":"纺织品商店里可没有日常百货或者五金商品。"}],"trans_cn":"纺织品商店"}]},{"name":"electrical goods store","pos":"n","guideword":" (shop selling electric devices)","trans_examp":[{"example":[{}],"trans_cn":"电子产品商店"}]},{"name":"fish store","pos":"n","guideword":" (shop that sells fish as pets)","trans_examp":[{"example":[{"eg":"The fish store sells a wide variety of tropical fish.","egtrans":""}],"trans_cn":"水族店"}]},{"name":"food store","pos":"n","guideword":" (grocery store)","trans_examp":[{"example":[{"eg":"","egtrans":""}],"trans_cn":"食品店, 杂货店"}]},{"name":"fruit store","pos":"n","guideword":" (shop selling fruit)","trans_examp":[{"example":[{"eg":"We purchased fresh strawberries from a local fruit store.","egtrans":""}],"trans_cn":"水果店"}]},{"name":"furniture store","pos":"n","guideword":" (shop: sells furnishings)","trans_examp":[{"example":[{"eg":"I went to the furniture store to look for a new sofa.","egtrans":""}],"trans_cn":"家具店"}]},{"name":"general store","pos":"n","guideword":" US (shop selling a variety of goods)","trans_examp":[{"example":[{"eg":"Because of big shopping malls and supermarkets, it's hard to find a general store these days.","egtrans":""}],"trans_cn":"杂货店"}]},{"name":"grocery store, grocery","pos":"n","guideword":" mainly US (supermarket, food shop)","trans_examp":[{"example":[{"eg":"Stella needed food, so she made a stop at the grocery store.","egtrans":"斯特拉需要食物，所以她顺道去了一趟杂货店。"}],"trans_cn":"杂货店, 杂货铺"}]},{"name":"hardware store","pos":"n","guideword":" (shop selling DIY or home-improvement supplies)","trans_examp":[{"example":[{"eg":"I went to the hardware store to buy a hammer.","egtrans":""}],"trans_cn":"五金商店, 五金店"}]},{"name":"have in store, hold in store","pos":"v expr","guideword":" (reserve, promise for the future)","trans_examp":[{"example":[{"eg":"Nobody knows what tomorrow has in store.","egtrans":""}],"trans_cn":"未来会有, 将来会发生什么"}]},{"name":"have [sth] in store for [sb], hold [sth] in store for [sb]","pos":"v expr","guideword":" (reserve, promise)","trans_examp":[{"example":[{"eg":"Let's wait and see what next year has in store for us.","egtrans":""}],"trans_cn":"…即将发生在某人头上, 有…等待着某人"}]},{"name":"health food store","pos":"n","guideword":" (shop selling organic and whole foods)","trans_examp":[{"example":[{"eg":"You can buy tofu in the health food store.","egtrans":""}],"trans_cn":"有机天然食品店, 健康食品店, 保健食品店"}]},{"name":"in store","pos":"adv","guideword":" (in reserve)","trans_examp":[{"example":[{"eg":"","egtrans":""}],"trans_cn":"储备着, 储藏着"}]},{"name":"in store","pos":"adv","guideword":" figurative (about to happen, for the future)","trans_examp":[{"example":[{"eg":"I always read my horoscope in the newspaper to find out what is in store for me.","egtrans":""}],"trans_cn":"将来, 将要发生"}]},{"name":"in store, in-store","pos":"adv","guideword":" (done within a store)","trans_examp":[{"example":[{"eg":"","egtrans":""}],"trans_cn":"店内, 在店内"}]},{"name":"in-store","pos":"adj","guideword":" (available within a store)","trans_examp":[{"example":[{}],"trans_cn":"店内的"}]},{"name":"in-store purchase","pos":"n","guideword":" ([sth] bought in person)","trans_examp":[{"example":[{}],"trans_cn":"实体店购物"}]},{"name":"jewelry store (US), jeweller's (UK)","pos":"n","guideword":" (sells, repairs jewelry)","trans_examp":[{"example":[{}],"trans_cn":"珠宝店"}]},{"name":"off-licence (UK), liquor store (US)","pos":"n","guideword":" (shop selling alcohol)","trans_examp":[{"example":[{"eg":"I stopped by the liquor store and bought a bottle of rum for tonight's party.","egtrans":""}],"trans_cn":"酒铺, 酒店"}]},{"name":"online store (US), online shop (UK)","pos":"n","guideword":" (internet shop)","trans_examp":[{"example":[{}],"trans_cn":"网上商店"}]},{"name":"pet store (US), pet shop (UK)","pos":"n","guideword":" (shop selling animals, feed, etc.)","trans_examp":[{"example":[{"eg":"The pet store sells a wide range of tropical fish.","egtrans":""}],"trans_cn":"宠物店"}]},{"name":"record store (US), record shop (UK)","pos":"n","guideword":" (store selling recorded music)","trans_examp":[{"example":[{}],"trans_cn":"唱片店"}]},{"name":"rental store (US), rental shop (UK)","pos":"n","guideword":" (business that hires [sth] out)","trans_examp":[{"example":[{}],"trans_cn":"租赁店"}]},{"name":"retail store","pos":"n","guideword":" (shop)","trans_examp":[{"example":[{"eg":"We have a retail store in the mall and a discount outlet store at the factory.","egtrans":""}],"trans_cn":"零售店"}]},{"name":"sales clerk. store clerk (US), sales assistant, shop assistant (UK)","pos":"n","guideword":" (store attendant)","trans_examp":[{"example":[{"eg":"If you need help locating something in the store, just ask a sales clerk.","egtrans":""}],"trans_cn":"售货员"}]},{"name":"shoe store (US), shoe shop (UK)","pos":"n","guideword":" (shop that sells footwear)","trans_examp":[{"example":[{}],"trans_cn":"鞋店"}]},{"name":"specialty store (US), speciality shop (UK)","pos":"n","guideword":" (specialized goods)","trans_examp":[{"example":[{"eg":"They only sell golf shoes in that specialty store.","egtrans":"那家专卖店里只出售高尔夫球鞋。"}],"trans_cn":"专卖店"}]},{"name":"stationer, stationer's, stationery shop","pos":"n","guideword":" UK (shop that sells writing materials)","trans_examp":[{"example":[{"eg":"The assistant went to the stationer's to buy more paper and pens.","egtrans":""}],"trans_cn":"文具店"}]},{"name":"stationery store","pos":"n","guideword":" US (stationer's: selling pens, paper, etc.)","trans_examp":[{"example":[{"eg":"The advent of electronic communications has all but killed the local stationery store.","egtrans":""}],"trans_cn":"文具店"}]},{"name":"store [sth] away","pos":"vtr + adv","guideword":" (keep)","trans_examp":[{"example":[{"eg":"Jim stored away provisions for emergencies.","egtrans":""}],"trans_cn":"把…储备起来, 存储"}]},{"name":"store card","pos":"n","guideword":" (customer credit card)","trans_examp":[{"example":[{"eg":"","egtrans":""}],"trans_cn":"商店信用卡, 客户信用卡"}]},{"name":"store card","pos":"n","guideword":" (shop's loyalty or reward card)","trans_examp":[{"example":[{"eg":"","egtrans":""}],"trans_cn":"商店会员卡, 商店积分卡"}]},{"name":"store credit","pos":"n","guideword":" (credit note)","trans_examp":[{"example":[{"eg":"","egtrans":""}],"trans_cn":"店铺抵用金, 商场信用积分"}]},{"name":"store manager","pos":"n","guideword":" ([sb] who runs a shop)","trans_examp":[{"example":[{"eg":"The clerk wouldn't give me a refund so I asked to speak to the store manager.","egtrans":""}],"trans_cn":"商店经理, 店铺经理"}]},{"name":"store owner","pos":"n","guideword":" US (proprietor of a shop)","trans_examp":[{"example":[{}],"trans_cn":"店主"}]},{"name":"store shed, storage shed","pos":"n","guideword":" (cabin for equipment)","trans_examp":[{"example":[{"eg":"Thieves broke into the store shed and stole a lawnmower.","egtrans":""}],"trans_cn":"储存棚，储存室"}]},{"name":"store-bought (US), shop-bought (UK)","pos":"adj","guideword":" (purchased ready-made)","trans_examp":[{"example":[{"eg":"Shop-bought bread lasts longer than home-made.","egtrans":""}],"trans_cn":"买来的"}]},{"name":"thrift store (US), charity shop (UK)","pos":"n","guideword":" (sells second-hand items)","trans_examp":[{"example":[{"eg":"I bought these vintage shirts at a thrift store.","egtrans":"这些复古衬衣我是在一家廉价旧货店买的。"}],"trans_cn":"廉价旧货商店"}]},{"name":"toy store (US), toy shop (UK)","pos":"n","guideword":" (store selling children's playthings)","trans_examp":[{"example":[{"eg":"In the weeks before Christmas, toy shops are packed.","egtrans":""}],"trans_cn":"玩具商店, 玩具店"}]},{"name":"video store, UK: video shop","pos":"n","guideword":" dated, US (shop selling videocassettes) (旧时用语)","trans_examp":[{"example":[{}],"trans_cn":"音像销售店，盒式录像带销售店"}]},{"name":"video store, UK: video shop","pos":"n","guideword":" dated, US (place for renting videocassettes) (旧时用语)","trans_examp":[{"example":[{"eg":"I'm going to the video store to get a movie for tonight.","egtrans":""}],"trans_cn":"音像租赁店，盒式录像带租赁店"}]}]}]