[{"name":"upgrade","pronunciation":{"uk":{"source":[{"type":"audio/mpeg","src":"/audio/en/uk/general/en094442.mp3"}],"class":"uk","phonetic":" verb: /ˌʌpˈgreɪd/,  noun: /ˈʌpgreɪd/"},"us":{"source":[{"type":"audio/mpeg","src":"/audio/en/us/us/en094442.mp3"}],"class":"us","phonetic":"/n. ˈʌpˌgreɪd; adj., adv. ˈʌpˈgreɪd; v. ʌpˈgreɪd, ˈʌpˌgreɪd/, (n. up′grād′; adj., adv. up′grād′; v. up grād′, up′grād′)"}},"dsense":[{"name":"upgrade [sth]⇒","pos":"vtr","guideword":" (install newer software) (计算机)","trans_examp":[{"example":[{"eg":"Glenn is upgrading his operating system.","egtrans":"格伦正在升级操作系统。"}],"trans_cn":"安装升级软件，升级（软件）"}]},{"name":"upgrade [sb]⇒","pos":"vtr","guideword":" (promote to next level)","trans_examp":[{"example":[{"eg":"The board decided to upgrade Elizabeth to manager.","egtrans":"董事会决定提拔伊丽莎白，让她做经理。"}],"trans_cn":"升…的职, 晋升, 提拔"}]},{"name":"upgrade [sb] to [sth]⇒","pos":"vtr","guideword":" (better seat, hotel, etc.) (入住的酒店房型，机舱座位级别等)","trans_examp":[{"example":[{"eg":"The airline company upgraded Dan to business class.","egtrans":"航空公司为丹升舱至商务舱。"}],"trans_cn":"为某人升级成, 为某人升舱至"}]},{"name":"upgrade⇒","pos":"vi","guideword":" (acquire newer software) (计算机软件)","trans_examp":[{"example":[{"eg":"This software is really out of date; you need to upgrade, if you want to stay competitive.","egtrans":"这个软件已经非常过时了，如果想要保持竞争性，你就得升级。"}],"trans_cn":"升级，更新换代"}]},{"name":"upgrade","pos":"n","guideword":" (act of upgrading) (品级等)","trans_examp":[{"example":[{"eg":"The council hoped the upgrade of the public transport system would lead to more people using it, instead of cars.","egtrans":"委员会希望随着公共交通系统的品级提升，将会有更多人使用它而非使用汽车。"}],"trans_cn":"提升，提高"}]},{"name":"upgrade","pos":"n","guideword":" (computing: newer software) (计算机软件)","trans_examp":[{"example":[{"eg":"Now we've completed the upgrade of our software, we shouldn't have a problem opening files anymore.","egtrans":"现在我们已经完成了软件的升级，打开文件时不应该再碰到任何问题了。"}],"trans_cn":"升级"}]},{"name":"upgrade","pos":"n","guideword":" (promotion to next level)","trans_examp":[{"example":[{"eg":"Agatha is hoping for an upgrade at her next performance review.","egtrans":"阿加莎正期盼着能在下一次绩效考核中获得一次升级。"}],"trans_cn":"升级, 提高级别, 提高档次"}]},{"name":"upgrade","pos":"n","guideword":" (better seat, hotel, etc.)","trans_examp":[{"example":[{"eg":"We were really lucky on our holiday; we got an upgrade to a luxury suite.","egtrans":"我们这次度假非常走运，酒店房型升到了豪华套间。"}],"trans_cn":"提高（乘客、旅客、酒店住客等的）待遇, 升..."}]}]},{"name":"upgrade","pronunciation":{"uk":{"source":[{"type":"audio/mpeg","src":"/audio/en/uk/general/en094442.mp3"}],"class":"uk","phonetic":" verb: /ˌʌpˈgreɪd/,  noun: /ˈʌpgreɪd/"},"us":{"source":[{"type":"audio/mpeg","src":"/audio/en/us/us/en094442.mp3"}],"class":"us","phonetic":"/n. ˈʌpˌgreɪd; adj., adv. ˈʌpˈgreɪd; v. ʌpˈgreɪd, ˈʌpˌgreɪd/, (n. up′grād′; adj., adv. up′grād′; v. up grād′, up′grād′)"}},"dsense":[{"name":"upgrade","pos":"n","guideword":" (new mobile phone) (手机)","trans_examp":[{"example":[{"eg":"Some mobile phone contracts include a free yearly upgrade.","egtrans":"一些手机套餐包含一年一次的免费升级换代。"}],"trans_cn":"升级，升级换代"}]},{"name":"upgrade [sth]⇒","pos":"vtr","guideword":" (increase rating of)","trans_examp":[{"example":[{"eg":"The government has upgraded the terror threat level from low to moderate.","egtrans":""}],"trans_cn":"提高…的级别"}]},{"name":"upgrade⇒","pos":"vtr","guideword":" (improve, modernize) (系统等)","trans_examp":[{"example":[{"eg":"We plan to upgrade all our company's systems to bring them more in line with the needs of today's customers.","egtrans":"我们计划升级公司所有的系统，让它们与时俱进，更符合当今客户的需求。"}],"trans_cn":"升级"}]},{"name":"upgrade","pos":"vtr","guideword":" (raise the quality of [sth])","trans_examp":[{"example":[{"eg":"Since they've had that new teacher, all the children in this class have upgraded their English skills.","egtrans":"自从他们换了新老师，班上所有孩子的英语水平都提升了。"}],"trans_cn":"提高，提升, 提高…的质量"}]},{"name":"upgrade [sth]⇒","pos":"vtr","guideword":" (mobile phone: get newer model) (手机)","trans_examp":[{"example":[{"eg":"Some people upgrade their phone every time a new model comes out, others keep the same phone for years.","egtrans":"有些人每次新机型一面世就会对自己的手机进行升级换代，其他人则会同一部手机使用多年。"}],"trans_cn":"升级，对…进行升级换代"}]}]}]