[{"name":"dot","pos":"noun","posTip":"A word that refers to a person, place, idea, event or thing.","pronunciation":{"uk":{"source":[{"type":"audio/mpeg","src":"/zhs/media/%E8%8B%B1%E8%AF%AD-%E6%B1%89%E8%AF%AD-%E7%AE%80%E4%BD%93/uk_pron/u/ukd/ukdop/ukdopie024.mp3"},{"type":"audio/ogg","src":"/zhs/media/%E8%8B%B1%E8%AF%AD-%E6%B1%89%E8%AF%AD-%E7%AE%80%E4%BD%93/uk_pron_ogg/u/ukd/ukdop/ukdopie024.ogg"}],"phonetic":"/dɒt/","class":"uk"},"us":{"source":[{"type":"audio/mpeg","src":"/zhs/media/%E8%8B%B1%E8%AF%AD-%E6%B1%89%E8%AF%AD-%E7%AE%80%E4%BD%93/us_pron/d/dot/dot__/dot.mp3"},{"type":"audio/ogg","src":"/zhs/media/%E8%8B%B1%E8%AF%AD-%E6%B1%89%E8%AF%AD-%E7%AE%80%E4%BD%93/us_pron_ogg/d/dot/dot__/dot.ogg"}],"phonetic":"/dɑːt/","class":"us"}},"dsense":[{"name":"","pos":"","guideword":"","trans_examp":[{"level":"B2","pos_2":"[ C ]","trans_en":"a very small round mark","trans_cn":"小圆点","example":[{"eg":"The full stop at the end of this sentence is a dot.","egtrans":"这个句子末尾的句号是一个小圆点。"},{"eg":"Her skirt was blue with white dots.","egtrans":"她的蓝裙子上有一些白色小圆点。"}]},{"level":"B1","pos_2":"[ U ]","trans_en":"the spoken form of a full stop in an internet or email address, or some computer files","trans_cn":"（互联网、电子邮件地址或某些计算机文件所使用的句号的口语形式）点","example":[{"eg":"\"What's the web address?\" \"www dot cambridge dot org\".","egtrans":"那个网址是什么? 「www.cambridge.org。」"}]},{"level":"","pos_2":"[ C ]","trans_en":"the short sounds or short flashes of light used with dashes when sending messages in Morse (code)","trans_cn":"（莫尔斯电码中的）点","example":[]}],"phrase":[]}]},{"name":"dot","pos":"verb","posTip":"A word that describes an action, condition or experience.","pronunciation":{"uk":{"source":[{"type":"audio/mpeg","src":"/zhs/media/%E8%8B%B1%E8%AF%AD-%E6%B1%89%E8%AF%AD-%E7%AE%80%E4%BD%93/uk_pron/u/ukd/ukdop/ukdopie024.mp3"},{"type":"audio/ogg","src":"/zhs/media/%E8%8B%B1%E8%AF%AD-%E6%B1%89%E8%AF%AD-%E7%AE%80%E4%BD%93/uk_pron_ogg/u/ukd/ukdop/ukdopie024.ogg"}],"phonetic":"/dɒt/","class":"uk"},"us":{"source":[{"type":"audio/mpeg","src":"/zhs/media/%E8%8B%B1%E8%AF%AD-%E6%B1%89%E8%AF%AD-%E7%AE%80%E4%BD%93/us_pron/d/dot/dot__/dot.mp3"},{"type":"audio/ogg","src":"/zhs/media/%E8%8B%B1%E8%AF%AD-%E6%B1%89%E8%AF%AD-%E7%AE%80%E4%BD%93/us_pron_ogg/d/dot/dot__/dot.ogg"}],"phonetic":"/dɑːt/","class":"us"}},"dsense":[{"name":"","pos":"","guideword":"","trans_examp":[{"level":"","pos_2":"[ T ]","trans_en":"to put a dot or dots on something","trans_cn":"在…上加点","example":[{"eg":"Your handwriting is hard to read because you don't dot your i's.","egtrans":"你的笔迹很难辨认，因为你在字母 I 上面不加点。"}]},{"level":"","pos_2":"[ T often passive ]","trans_en":"to be spread across an area, or to spread many similar things across an area","trans_cn":"分布，分散","example":[{"eg":"We have offices dotted around/all over the region.","egtrans":"我们的办事处在该地区星罗棋布。"},{"eg":"The area is dotted with beautiful churches.","egtrans":"这一地区有很多漂亮的教堂。"}]}],"phrase":[]}]}]