[{"name":"flag","pos":"noun [ C ]","posTip":"A word that refers to a person, place, idea, event or thing.","pronunciation":{"uk":{"source":[{"type":"audio/mpeg","src":"/zhs/media/%E8%8B%B1%E8%AF%AD-%E6%B1%89%E8%AF%AD-%E7%AE%80%E4%BD%93/uk_pron/u/ukf/ukfla/ukflacc003.mp3"},{"type":"audio/ogg","src":"/zhs/media/%E8%8B%B1%E8%AF%AD-%E6%B1%89%E8%AF%AD-%E7%AE%80%E4%BD%93/uk_pron_ogg/u/ukf/ukfla/ukflacc003.ogg"}],"phonetic":"/flæɡ/","class":"uk"},"us":{"source":[{"type":"audio/mpeg","src":"/zhs/media/%E8%8B%B1%E8%AF%AD-%E6%B1%89%E8%AF%AD-%E7%AE%80%E4%BD%93/us_pron/f/fla/flag_/flag.mp3"},{"type":"audio/ogg","src":"/zhs/media/%E8%8B%B1%E8%AF%AD-%E6%B1%89%E8%AF%AD-%E7%AE%80%E4%BD%93/us_pron_ogg/f/fla/flag_/flag.ogg"}],"phonetic":"/flæɡ/","class":"us"}},"dsense":[{"name":"flag","pos":"noun","posTip":"A word that refers to a person, place, idea, event or thing.","guideword":"\n            (SYMBOL)\n      ","trans_examp":[{"level":"B1","pos_2":"","trans_en":"a piece of cloth, usually rectangular and attached to a pole at one edge, that has a pattern that shows it represents a country or a group, or has a particular meaning","trans_cn":"旗，旗帜","example":[{"eg":"Flags of all the participating countries are flying outside the stadium.","egtrans":"所有参赛国家的国旗都飘扬在体育场外。"},{"eg":"Flags were flapping/fluttering in the breeze.","egtrans":"旗子在和风中飘扬。"},{"eg":"The guard waved his flag and the train pulled away from the station.","egtrans":"护卫挥旗示意，火车从车站驶离。"}]}],"phrase":[]},{"name":"flag","pos":"noun","posTip":"A word that refers to a person, place, idea, event or thing.","guideword":"\n            (STONE)\n      ","trans_examp":[{"level":"","pos_2":"","trans_en":"a \n        \n         flagstone  ","trans_cn":"（同 flagstone）","example":[]}],"phrase":[]},{"name":"flag","pos":"noun","posTip":"A word that refers to a person, place, idea, event or thing.","guideword":"\n            (PLANT)\n      ","trans_examp":[{"level":"","pos_2":"","trans_en":"a flower that is a type of large iris","trans_cn":"菖蒲（一种大型鸢尾花）","example":[]}],"phrase":[]}]},{"name":"flag","pos":"verb","posTip":"A word that describes an action, condition or experience.","pronunciation":{"uk":{"source":[{"type":"audio/mpeg","src":"/zhs/media/%E8%8B%B1%E8%AF%AD-%E6%B1%89%E8%AF%AD-%E7%AE%80%E4%BD%93/uk_pron/u/ukf/ukfla/ukflacc003.mp3"},{"type":"audio/ogg","src":"/zhs/media/%E8%8B%B1%E8%AF%AD-%E6%B1%89%E8%AF%AD-%E7%AE%80%E4%BD%93/uk_pron_ogg/u/ukf/ukfla/ukflacc003.ogg"}],"phonetic":"/flæɡ/","class":"uk"},"us":{"source":[{"type":"audio/mpeg","src":"/zhs/media/%E8%8B%B1%E8%AF%AD-%E6%B1%89%E8%AF%AD-%E7%AE%80%E4%BD%93/us_pron/f/fla/flag_/flag.mp3"},{"type":"audio/ogg","src":"/zhs/media/%E8%8B%B1%E8%AF%AD-%E6%B1%89%E8%AF%AD-%E7%AE%80%E4%BD%93/us_pron_ogg/f/fla/flag_/flag.ogg"}],"phonetic":"/flæɡ/","class":"us"}},"dsense":[{"name":"flag","pos":"verb","posTip":"A word that describes an action, condition or experience.","guideword":"\n            (MARK)\n      ","trans_examp":[{"level":"","pos_2":"[ T ]","trans_en":"to put a mark on something so it can be found easily among other similar things","trans_cn":"给…做标记","example":[{"eg":"Flag any files that might be useful later.","egtrans":"给日后可能有用的文件做上标记。"}]},{"level":"","pos_2":"[ T ]","trans_en":"to mark computer information with one of two possible values so that you can deal with it later","trans_cn":"标记（计算机里某些信息，以便之后处理）","example":[{"eg":"We'll flag the records of interest in the database and then we can give you a print-out.","egtrans":"我们会在数据库中把值得关注的纪录标记出来，之后打印一份给你。"}]}],"phrase":[]},{"name":"flag","pos":"verb","posTip":"A word that describes an action, condition or experience.","guideword":"\n            (BECOME TIRED)\n      ","trans_examp":[{"level":"","pos_2":"[ I ]","trans_en":"to become tired, weaker, or less effective","trans_cn":"变得疲倦；兴趣衰减","example":[{"eg":"I was starting to flag after the ninth mile.","egtrans":"走了9英里后，我开始感到疲倦了。"},{"eg":"The conversation was flagging.","egtrans":"谈话越来越乏味了。"}]}],"phrase":[]}]}]