[{"name":"handbook","pos":"noun [ C ]","posTip":"A word that refers to a person, place, idea, event or thing.","pronunciation":{"uk":{"source":[{"type":"audio/mpeg","src":"/zhs/media/%E8%8B%B1%E8%AF%AD-%E6%B1%89%E8%AF%AD-%E7%AE%80%E4%BD%93/uk_pron/u/ukh/ukhan/ukhandb002.mp3"},{"type":"audio/ogg","src":"/zhs/media/%E8%8B%B1%E8%AF%AD-%E6%B1%89%E8%AF%AD-%E7%AE%80%E4%BD%93/uk_pron_ogg/u/ukh/ukhan/ukhandb002.ogg"}],"phonetic":"/ˈhænd.bʊk/","class":"uk"},"us":{"source":[{"type":"audio/mpeg","src":"/zhs/media/%E8%8B%B1%E8%AF%AD-%E6%B1%89%E8%AF%AD-%E7%AE%80%E4%BD%93/us_pron/h/han/handb/handbook.mp3"},{"type":"audio/ogg","src":"/zhs/media/%E8%8B%B1%E8%AF%AD-%E6%B1%89%E8%AF%AD-%E7%AE%80%E4%BD%93/us_pron_ogg/h/han/handb/handbook.ogg"}],"phonetic":"/ˈhænd.bʊk/","class":"us"}},"dsense":[{"name":"","pos":"","guideword":"","trans_examp":[{"level":"","pos_2":"","trans_en":"a book that contains instructions or advice about how to do something or the most important and useful information about a subject","trans_cn":"手册，指南","example":[{"eg":"The student handbook gives details of all courses.","egtrans":"学生手册中有所有课程的详细介绍。"}]}],"phrase":[]}]}]