[{"name":"since","pos":"adverb","posTip":"A word that describes or gives more information about a verb, adjective or other adverb.","pronunciation":{"uk":{"source":[{"type":"audio/mpeg","src":"/zhs/media/%E8%8B%B1%E8%AF%AD-%E6%B1%89%E8%AF%AD-%E7%AE%80%E4%BD%93/uk_pron/u/uks/uksim/uksimil026.mp3"},{"type":"audio/ogg","src":"/zhs/media/%E8%8B%B1%E8%AF%AD-%E6%B1%89%E8%AF%AD-%E7%AE%80%E4%BD%93/uk_pron_ogg/u/uks/uksim/uksimil026.ogg"}],"phonetic":"/sɪns/","class":"uk"},"us":{"source":[{"type":"audio/mpeg","src":"/zhs/media/%E8%8B%B1%E8%AF%AD-%E6%B1%89%E8%AF%AD-%E7%AE%80%E4%BD%93/us_pron/s/sin/since/since.mp3"},{"type":"audio/ogg","src":"/zhs/media/%E8%8B%B1%E8%AF%AD-%E6%B1%89%E8%AF%AD-%E7%AE%80%E4%BD%93/us_pron_ogg/s/sin/since/since.ogg"}],"phonetic":"/sɪns/","class":"us"}},"dsense":[{"name":"","pos":"","guideword":"","trans_examp":[{"level":"B2","pos_2":"","trans_en":"from a particular time in the past until a later time, or until now","trans_cn":"此后，从此","example":[{"eg":"Emma went to work in New York a year ago, and we haven't seen her since.","egtrans":"埃玛一年前去纽约工作了，自那时起我们就没有见过她。"},{"eg":"He started working for the company in 1995, and has been there ever since (= and is still there).","egtrans":"他1995年就开始为那家公司工作，在此之后就一直在那里。"},{"eg":"I've long since (= long ago) forgotten any Latin I ever learned.","egtrans":"我早就把我学过的那点拉丁语忘光了。"}]}],"phrase":[]}]},{"name":"since","pos":"preposition","posTip":"Word used before noun, pronoun or -ing form of verb to show place, direction, etc.","pronunciation":{"uk":{"source":[{"type":"audio/mpeg","src":"/zhs/media/%E8%8B%B1%E8%AF%AD-%E6%B1%89%E8%AF%AD-%E7%AE%80%E4%BD%93/uk_pron/u/uks/uksim/uksimil026.mp3"},{"type":"audio/ogg","src":"/zhs/media/%E8%8B%B1%E8%AF%AD-%E6%B1%89%E8%AF%AD-%E7%AE%80%E4%BD%93/uk_pron_ogg/u/uks/uksim/uksimil026.ogg"}],"phonetic":"/sɪns/","class":"uk"},"us":{"source":[{"type":"audio/mpeg","src":"/zhs/media/%E8%8B%B1%E8%AF%AD-%E6%B1%89%E8%AF%AD-%E7%AE%80%E4%BD%93/us_pron/s/sin/since/since.mp3"},{"type":"audio/ogg","src":"/zhs/media/%E8%8B%B1%E8%AF%AD-%E6%B1%89%E8%AF%AD-%E7%AE%80%E4%BD%93/us_pron_ogg/s/sin/since/since.ogg"}],"phonetic":"/sɪns/","class":"us"}},"dsense":[{"name":"","pos":"","guideword":"","trans_examp":[{"level":"A2","pos_2":"","trans_en":"from a particular time in the past until a later time, or until now","trans_cn":"自从…；从…以来","example":[{"eg":"He hasn't won a game since last year. ","egtrans":"他自去年起就再没有赢过比赛。"},{"eg":"It was the hottest October since records began.","egtrans":"这是有史以来最热的十月。"}]}],"phrase":[]}]},{"name":"since","pos":"conjunction","posTip":"A word used to join parts of a phrase or sentence.","pronunciation":{"uk":{"source":[{"type":"audio/mpeg","src":"/zhs/media/%E8%8B%B1%E8%AF%AD-%E6%B1%89%E8%AF%AD-%E7%AE%80%E4%BD%93/uk_pron/u/uks/uksim/uksimil026.mp3"},{"type":"audio/ogg","src":"/zhs/media/%E8%8B%B1%E8%AF%AD-%E6%B1%89%E8%AF%AD-%E7%AE%80%E4%BD%93/uk_pron_ogg/u/uks/uksim/uksimil026.ogg"}],"phonetic":"/sɪns/","class":"uk"},"us":{"source":[{"type":"audio/mpeg","src":"/zhs/media/%E8%8B%B1%E8%AF%AD-%E6%B1%89%E8%AF%AD-%E7%AE%80%E4%BD%93/us_pron/s/sin/since/since.mp3"},{"type":"audio/ogg","src":"/zhs/media/%E8%8B%B1%E8%AF%AD-%E6%B1%89%E8%AF%AD-%E7%AE%80%E4%BD%93/us_pron_ogg/s/sin/since/since.ogg"}],"phonetic":"/sɪns/","class":"us"}},"dsense":[{"name":"since","pos":"conjunction","posTip":"A word used to join parts of a phrase or sentence.","guideword":"\n            (BECAUSE)\n      ","trans_examp":[{"level":"B1","pos_2":"","trans_en":"because; as","trans_cn":"因为；既然","example":[{"eg":"Since we've got a few minutes to wait for the train, let's have a cup of coffee.","egtrans":"既然等火车还需要几分钟，我们去喝杯咖啡吧。"}]}],"phrase":[]},{"name":"since","pos":"conjunction","posTip":"A word used to join parts of a phrase or sentence.","guideword":"\n            (TIME)\n      ","trans_examp":[{"level":"B1","pos_2":"","trans_en":"from a particular time in the past until a later time, or until now","trans_cn":"自从…；从…以来","example":[{"eg":"I've been very busy since I came back from holiday.","egtrans":"我度完假回来后就一直很忙。"}]}],"phrase":[]}]}]